bluffai/__init__.py
bluffai/__version__.py
bluffai-0.1.1.dist-info/METADATA
bluffai-0.1.1.dist-info/WHEEL
bluffai-0.1.1.dist-info/entry_points.txt
bluffai-0.1.1.dist-info/RECORD
